alphagot/__init__.py
alphagot-0.0.2.dist-info/LICENSE
alphagot-0.0.2.dist-info/METADATA
alphagot-0.0.2.dist-info/WHEEL
alphagot-0.0.2.dist-info/top_level.txt
alphagot-0.0.2.dist-info/RECORD
