Metadata-Version: 2.1
Name: alphagot
Version: 0.0.2
Summary: alphagot nft
Author-email: alphagot <alphagot@163.com>
Project-URL: Homepage, https://github.com/alphagot812/alphagot
Project-URL: Issues, https://github.com/alphagot812/alphagot/issues
Project-URL: Source, https://github.com/alphagot812/alphagot
Classifier: Programming Language :: Python :: 3
Classifier: License :: OSI Approved :: MIT License
Classifier: Operating System :: OS Independent
Requires-Python: >=3.8
License-File: LICENSE
